{
  "global": {},
  "Color/Mode 1": {
    "Color": {
      "Brand": {
        "Primary 50": {
          "value": "#81ac0d",
          "type": "color"
        },
        "Tertiary": {
          "value": "#539d93",
          "type": "color"
        },
        "Secondry": {
          "value": "#89966d",
          "type": "color"
        }
      },
      "Neutral": {
        "50": {
          "value": "#91918a",
          "type": "color"
        },
        "50 2": {
          "value": "#9d9f91",
          "type": "color"
        },
        "50 3": {
          "value": "#a7aa99",
          "type": "color"
        },
        "50 4": {
          "value": "#909284",
          "type": "color"
        },
        "50 5": {
          "value": "#abac9e",
          "type": "color"
        },
        "50 6": {
          "value": "#abac9e",
          "type": "color"
        }
      },
      "UI States": {
        "Success": {
          "value": "#61d735",
          "type": "color"
        },
        "Warning": {
          "value": "#fd731e",
          "type": "color"
        },
        "Error": {
          "value": "#ef4444",
          "type": "color"
        }
      },
      "Special": {
        "White": {
          "value": "#ffffff",
          "type": "color"
        },
        "Black": {
          "value": "#000000",
          "type": "color"
        }
      }
    }
  },
  "Boolean/Mode 1": {
    "State": {
      "IsDisabled": {
        "value": "false",
        "type": "boolean",
        "description": "نشان می‌دهد المان در حالت غیرفعال (غیرقابل کلیک/ویرایش) است یا نه."
      },
      "IsLoading": {
        "value": "false",
        "type": "boolean",
        "description": "برای نمایش حالت در حال بارگذاری؛ متن/آیکون می‌تواند با اسپینر جایگزین شود."
      },
      "IsSelected": {
        "value": "false",
        "type": "boolean",
        "description": "برای موارد انتخاب‌شونده مثل کارت، آیتم لیست، تب یا چک‌با‌کس."
      },
      "IsActive": {
        "value": "false",
        "type": "boolean",
        "description": "برای آیتم‌های فعال مثل تب فعال، منوی فعال یا مسیر فعلی ناوبری."
      },
      "IsFocused": {
        "value": "false",
        "type": "boolean",
        "description": "نشان‌دهنده فوکوس فعلی روی فیلد یا دکمه (برای حالت‌های Focus)."
      },
      "IsError": {
        "value": "false",
        "type": "boolean",
        "description": "برای نشان‌دادن اینکه المان در حالت خطا است (مثلاً ورودی نامعتبر)."
      },
      "IsSuccess": {
        "value": "false",
        "type": "boolean",
        "description": "برای نمایش حالت موفقیت در المان‌ها، مثل استیت موفق دکمه یا پیام."
      },
      "IsReadOnly": {
        "value": "false",
        "type": "boolean",
        "description": "نشان می‌دهد فیلد فقط خواندنی است و کاربر نمی‌تواند آن را تغییر دهد."
      },
      "IsRequired": {
        "value": "false",
        "type": "boolean",
        "description": "برای مشخص‌کردن الزامی بودن فیلد یا بخش فرم."
      }
    },
    "Festure": {
      "HasIcon": {
        "value": "false",
        "type": "boolean",
        "description": "برای کامپوننت‌هایی که یک آیکون ساده دارند (مثلاً دکمه یا اینپوت)."
      },
      "HasLeadingIcon": {
        "value": "false",
        "type": "boolean",
        "description": "نمایش یا عدم نمایش آیکون در ابتدای المان (چپ/راست بسته به زبان)."
      },
      "HasTrailingIcon": {
        "value": "false",
        "type": "boolean",
        "description": "نمایش یا عدم نمایش آیکون انتهای المان (مثلاً فلش در دکمه)."
      },
      "HasBadge": {
        "value": "false",
        "type": "boolean",
        "description": "برای افزودن یا حذف نشان (badge) کنار متن یا آیکون."
      },
      "IsDismissible": {
        "value": "false",
        "type": "boolean",
        "description": "برای کامپوننت‌هایی که قابلیت بسته‌شدن توسط کاربر دارند (مثل Alert یا Modal)."
      },
      "HasHelperText": {
        "value": "false",
        "type": "boolean",
        "description": "برای کنترل نمایش متن راهنما زیر فیلدها یا المان‌ها."
      }
    },
    "Layout": {
      "IsOne": {
        "value": "false",
        "type": "boolean",
        "description": "باز یا بسته بودن یک پنجره، modal، drawer یا منوی کشویی را مشخص می‌کند."
      },
      "IsExpanded": {
        "value": "false",
        "type": "boolean",
        "description": "برای آکاردئون‌ها، کارت‌های قابل گسترش یا بخش‌های بازشونده."
      },
      "IsCollapsed": {
        "value": "false",
        "type": "boolean",
        "description": "برعکس isExpanded؛ نمایش حالت جمع‌شده‌ی بخش‌ها."
      },
      "IsSticky": {
        "value": "false",
        "type": "boolean",
        "description": "برای هدریا نوارهایی که باید در بالا ثابت بمانند."
      }
    }
  },
  "String/Mode 1": {
    "Button": {
      "PrimaryLable": {
        "value": "ادامه",
        "type": "text"
      },
      "SecoundryLable": {
        "value": "لغو",
        "type": "text"
      },
      "TeriaryLable": {
        "value": "بیشتر",
        "type": "text"
      },
      "Loading": {
        "value": "در حال بارگذاری ...",
        "type": "text"
      },
      "Success": {
        "value": "انجام شد",
        "type": "text"
      },
      "Error": {
        "value": "خطا",
        "type": "text"
      },
      "Save": {
        "value": "ذخیره",
        "type": "text"
      },
      "Edit": {
        "value": "ویرایش",
        "type": "text"
      },
      "Delet": {
        "value": "حذف",
        "type": "text"
      },
      "Confirm": {
        "value": "تائید",
        "type": "text"
      },
      "Cancle": {
        "value": "انصراف",
        "type": "text"
      },
      "Back": {
        "value": "بازگشت",
        "type": "text"
      },
      "SeeMore": {
        "value": "مشاهده بیشتر",
        "type": "text"
      },
      "Close": {
        "value": "بستن",
        "type": "text"
      },
      "Apply": {
        "value": "اعمال",
        "type": "text"
      },
      "Rest": {
        "value": "خطا",
        "type": "text"
      }
    },
    "Input": {
      "EmailPlaceholder": {
        "value": "ایمیل",
        "type": "text"
      },
      "PasswordPlaceholder": {
        "value": "رمز عبور",
        "type": "text"
      },
      "SearchPlaceholder": {
        "value": "جستجو ...",
        "type": "text"
      },
      "NamePlaceholder": {
        "value": "نام و نام خانوادگی",
        "type": "text"
      },
      "PhonePlaceholder": {
        "value": "شماره موبایل",
        "type": "text"
      },
      "UserNamePlaceholder": {
        "value": "نام کاربری",
        "type": "text"
      },
      "CodePlaceholder": {
        "value": "کد تائید",
        "type": "text"
      },
      "OptionalSuffix": {
        "value": "(اختیاری)",
        "type": "text"
      }
    },
    "Lable": {
      "Email": {
        "value": "ایمیل",
        "type": "text"
      },
      "Password": {
        "value": "رمز عبور",
        "type": "text"
      },
      "Name": {
        "value": "نام",
        "type": "text"
      },
      "Phone": {
        "value": "شماره موبایل",
        "type": "text"
      },
      "Search": {
        "value": "جستجو",
        "type": "text"
      },
      "LastName": {
        "value": "نام خانوادگی",
        "type": "text"
      },
      "UserName": {
        "value": "نام کاربری",
        "type": "text"
      },
      "City": {
        "value": "شهر",
        "type": "text"
      },
      "RememberMe": {
        "value": "مرا به خاطر بسپار",
        "type": "text"
      },
      "TermsAgree": {
        "value": "قوانین و شرایط را می‌پذیرم",
        "type": "text"
      },
      "Address": {
        "value": "آدرس",
        "type": "text"
      }
    },
    "Helper": {
      "PasswordHint": {
        "value": "رمز عبور باید حداقل 8 کاراکتر باشد",
        "type": "text"
      },
      "RequiredHint": {
        "value": "فیلدهای دارای * الزامی هستند",
        "type": "text"
      },
      "PhoneHint": {
        "value": "شماره موبایل را با فرمت صحیح وارد کنید",
        "type": "text"
      },
      "EmailHint": {
        "value": "ایمیل برای بازیابی حساب استفاده می‌شود",
        "type": "text"
      }
    },
    "Message": {
      "SuccessGenertic": {
        "value": "عملیات با موفقیت انجام شد",
        "type": "text"
      },
      "ErrorGenertic": {
        "value": "در انجام عملیات خطایی رخ داد",
        "type": "text"
      },
      "Saved": {
        "value": "تغییرات با موفقیت انجام شد",
        "type": "text"
      },
      "Loading": {
        "value": "در حال بارگذاری ...",
        "type": "text"
      },
      "Deleted": {
        "value": "آیتم با موفقیت حذف شد",
        "type": "text"
      },
      "TryAgain": {
        "value": "لطفا مجدد تلاش کنید",
        "type": "text"
      },
      "NonAccess": {
        "value": "در حال بارگذاری ...",
        "type": "text"
      }
    },
    "Error": {
      "ErrorRequired": {
        "value": "پر کردن این فیلد ضرروری است",
        "type": "text"
      },
      "ErrorInvalidEmail": {
        "value": "ایمیل وارد شده معتبر نیست",
        "type": "text"
      },
      "ErrorMinLength": {
        "value": "طول متن کمتر از حد مجاز است",
        "type": "text"
      },
      "ErrorMaxLength": {
        "value": "طول متن بیشتر از حد مجاز است",
        "type": "text"
      },
      "ErrorInvalidForm": {
        "value": "فرمت اطلاعات صحیح نیست",
        "type": "text"
      }
    },
    "Empty": {
      "ListTitle": {
        "value": "موردی برای نمایش وجود ندارد",
        "type": "text"
      },
      "ListDesc": {
        "value": "می‌توانید از دکمه بالا برای افزودن مورد جدید استفاده کنید",
        "type": "text"
      },
      "SearchTitle": {
        "value": "نتیجه‌ای یافت نشد",
        "type": "text"
      },
      "SearchDesc": {
        "value": "عبارت جستجو را تغییر دهید و دوباره امتحان کنید",
        "type": "text"
      },
      "FavortestTitle": {
        "value": "هنوز موردی به علاقه‌مندی‌ها اضافه نکرده‌اید",
        "type": "text"
      },
      "FavortestDesc": {
        "value": "با انتخاب آیکون ♥ می‌توانید موارد مورد علاقه را ذخیره",
        "type": "text"
      }
    },
    "Nav": {
      "Home": {
        "value": "خانه",
        "type": "text"
      },
      "Dashboard": {
        "value": "داشبورد",
        "type": "text"
      },
      "Profile": {
        "value": "پروفایل",
        "type": "text"
      },
      "Setting": {
        "value": "تنظیمات",
        "type": "text"
      },
      "Logout": {
        "value": "خروج",
        "type": "text"
      },
      "Login": {
        "value": "ورود",
        "type": "text"
      },
      "Register": {
        "value": "ثبت نام",
        "type": "text"
      },
      "Help": {
        "value": "راهنما",
        "type": "text"
      },
      "Support": {
        "value": "پشتیبانی",
        "type": "text"
      }
    },
    "Table": {
      "EmptyTitle": {
        "value": "داده‌ای برای نمایش وجود ندارد",
        "type": "text"
      },
      "EmptyDesc": {
        "value": "به‌محض ثبت اطلاعات، اینجا نمایش داده می‌شود",
        "type": "text"
      },
      "Header": {
        "Action": {
          "value": "عملیات",
          "type": "text"
        },
        "Status": {
          "value": "وضعیت",
          "type": "text"
        },
        "Date": {
          "value": "تاریخ",
          "type": "text"
        },
        "Name": {
          "value": "نام",
          "type": "text"
        },
        "Price": {
          "value": "قیمت",
          "type": "text"
        }
      }
    },
    "Filter": {
      "Title": {
        "value": "فیلترها",
        "type": "text"
      },
      "Apply": {
        "value": "اعمال فیلتر",
        "type": "text"
      },
      "Reset": {
        "value": "حذف فیلترها",
        "type": "text"
      },
      "SortBy": {
        "value": "مرتب‌سازی بر اساس",
        "type": "text"
      },
      "SortNewest": {
        "value": "جدیدترین",
        "type": "text"
      },
      "SortOldest": {
        "value": "قدیمی‌ترین",
        "type": "text"
      },
      "SortCheapest": {
        "value": "ارزان‌ترین",
        "type": "text"
      },
      "SortExpensive": {
        "value": "گران‌ترین",
        "type": "text"
      }
    },
    "Auth": {
      "LoginTitle": {
        "value": "ورود به حساب کاربری",
        "type": "text"
      },
      "RegisterTitle": {
        "value": "ایجاد حساب جدید",
        "type": "text"
      },
      "ForgotTitle": {
        "value": "بازیابی رمز عبور",
        "type": "text"
      },
      "LoginDesc": {
        "value": "برای ادامه، وارد حساب کاربری خود شوید",
        "type": "text"
      },
      "RegisterDesc": {
        "value": "با چند مرحله ساده، حساب خود را ایجاد کنید",
        "type": "text"
      },
      "ForgotDesc": {
        "value": "ایمیل خود را وارد کنید تا لینک بازیابی برای شما ارسال شود",
        "type": "text"
      },
      "NoAccount": {
        "value": "حساب کاربری ندارید؟",
        "type": "text"
      },
      "HaveAccount": {
        "value": "از قبل حساب دارید؟",
        "type": "text"
      },
      "GoToRegister": {
        "value": "ثبت‌نام",
        "type": "text"
      },
      "GoToLogin": {
        "value": "ورود",
        "type": "text"
      },
      "ResendCode": {
        "value": "ارسال مجدد کد",
        "type": "text"
      }
    },
    "Modal": {
      "ConfirmTitle": {
        "value": "آیا مطمئن هستید؟",
        "type": "text"
      },
      "ConfirmDesc": {
        "value": "این عملیات ممکن است غیرقابل بازگشت باشد",
        "type": "text"
      },
      "DeleteTitle": {
        "value": "حذف آیتم",
        "type": "text"
      },
      "DeleteDesc": {
        "value": "آیا از حذف این آیتم اطمینان دارید؟",
        "type": "text"
      },
      "CloseWarning": {
        "value": "با بستن این پنجره، تغییرات ذخیره نمی‌شود",
        "type": "text"
      }
    }
  },
  "Typography/Mode 1": {
    "H1": {
      "FontSize": {
        "Mobile": {
          "value": 32,
          "type": "number"
        },
        "Tablet": {
          "value": 40,
          "type": "number"
        },
        "Desktop": {
          "value": 48,
          "type": "number"
        }
      },
      "LineHeight": {
        "Mobile": {
          "value": 38.4,
          "type": "number"
        },
        "Tablet": {
          "value": 48,
          "type": "number"
        },
        "Desktop": {
          "value": 57.6,
          "type": "number"
        }
      },
      "Weight": {
        "Mobile": {
          "value": 700,
          "type": "number"
        },
        "Tablet": {
          "value": 700,
          "type": "number"
        },
        "Desktop": {
          "value": 700,
          "type": "number"
        }
      },
      "ParagraphSpacing": {
        "Mobile": {
          "value": 16,
          "type": "number"
        },
        "Tablet": {
          "value": 20,
          "type": "number"
        },
        "Desktop": {
          "value": 0,
          "type": "number"
        }
      }
    },
    "H2": {
      "FontSize": {
        "Mobile": {
          "value": 28,
          "type": "number"
        },
        "Tablet": {
          "value": 32,
          "type": "number"
        },
        "Desktop": {
          "value": 40,
          "type": "number"
        }
      },
      "Weight": {
        "Mobile": {
          "value": 600,
          "type": "number"
        },
        "Tablet": {
          "value": 600,
          "type": "number"
        },
        "Desktop": {
          "value": 600,
          "type": "number"
        }
      },
      "LineHeight": {
        "Mobile": {
          "value": 34,
          "type": "number"
        },
        "Tablet": {
          "value": 40,
          "type": "number"
        },
        "Desktop": {
          "value": 45,
          "type": "number"
        }
      },
      "ParagraphSpacing": {
        "Mobile": {
          "value": 12,
          "type": "number"
        },
        "Tablet": {
          "value": 16,
          "type": "number"
        },
        "Desktop": {
          "value": 0,
          "type": "number"
        }
      }
    },
    "H3": {
      "FontSize": {
        "Mobile": {
          "value": 24,
          "type": "number"
        },
        "Tablet": {
          "value": 28,
          "type": "number"
        },
        "Desktop": {
          "value": 32,
          "type": "number"
        }
      },
      "LineHeight": {
        "Mobile": {
          "value": 31.2,
          "type": "number"
        },
        "Tablet": {
          "value": 36.4,
          "type": "number"
        },
        "Desktop": {
          "value": 41.6,
          "type": "number"
        }
      },
      "Weight": {
        "Mobile": {
          "value": 600,
          "type": "number"
        },
        "Tablet": {
          "value": 600,
          "type": "number"
        },
        "Desktop": {
          "value": 600,
          "type": "number"
        }
      },
      "ParagraphSpacing": {
        "Mobile": {
          "value": 12,
          "type": "number"
        },
        "Tablet": {
          "value": 14,
          "type": "number"
        },
        "Desktop": {
          "value": 0,
          "type": "number"
        }
      }
    },
    "Body": {
      "FontSize": {
        "Mobile": {
          "value": 15,
          "type": "number"
        },
        "Tablet": {
          "value": 16,
          "type": "number"
        },
        "Desktop": {
          "value": 18,
          "type": "number"
        }
      },
      "LineHeight": {
        "Mobile": {
          "value": 22.5,
          "type": "number"
        },
        "Tablet": {
          "value": 24,
          "type": "number"
        },
        "Desktop": {
          "value": 27,
          "type": "number"
        }
      },
      "Weight": {
        "Mobile": {
          "value": 400,
          "type": "number"
        },
        "Tablet": {
          "value": 400,
          "type": "number"
        },
        "Desktop": {
          "value": 0,
          "type": "number"
        }
      },
      "ParagraphSpacing": {
        "Mobile": {
          "value": 8,
          "type": "number"
        },
        "Tablet": {
          "value": 10,
          "type": "number"
        },
        "Desktop": {
          "value": 0,
          "type": "number"
        }
      }
    },
    "Caption": {
      "FontSize": {
        "Mobile": {
          "value": 13,
          "type": "number"
        },
        "Tablet": {
          "value": 14,
          "type": "number"
        },
        "Desktop": {
          "value": 14,
          "type": "number"
        }
      },
      "LineHeight": {
        "Mobile": {
          "value": 18.5,
          "type": "number"
        },
        "Tablet": {
          "value": 19.6,
          "type": "number"
        },
        "Desktop": {
          "value": 19.6,
          "type": "number"
        }
      },
      "Weight": {
        "Mobile": {
          "value": 400,
          "type": "number"
        },
        "Tablet": {
          "value": 400,
          "type": "number"
        },
        "Desktop": {
          "value": 400,
          "type": "number"
        }
      },
      "ParagraphSpacing": {
        "Mobile": {
          "value": 4,
          "type": "number"
        },
        "Tablet": {
          "value": 6,
          "type": "number"
        },
        "Desktop": {
          "value": 8,
          "type": "number"
        }
      }
    },
    "Button": {
      "FontSize": {
        "Mobile": {
          "value": 15,
          "type": "number"
        },
        "Tablet": {
          "value": 16,
          "type": "number"
        },
        "Desktop": {
          "value": 16,
          "type": "number"
        }
      },
      "LineHeight": {
        "Mobile": {
          "value": 18,
          "type": "number"
        },
        "Tablet": {
          "value": 19.2,
          "type": "number"
        },
        "Desktop": {
          "value": 19.2,
          "type": "number"
        }
      },
      "Weight": {
        "Mobile": {
          "value": 600,
          "type": "number"
        },
        "Tablet": {
          "value": 600,
          "type": "number"
        },
        "Desktop": {
          "value": 600,
          "type": "number"
        }
      }
    },
    "Lable": {
      "Weight": {
        "Mobile": {
          "value": 500,
          "type": "number"
        },
        "Tablet": {
          "value": 500,
          "type": "number"
        },
        "Desktop": {
          "value": 500,
          "type": "number"
        }
      },
      "FontSize": {
        "Mobile": {
          "value": 12,
          "type": "number"
        },
        "Tablet": {
          "value": 12,
          "type": "number"
        },
        "Desktop": {
          "value": 0,
          "type": "number"
        }
      },
      "LineHeight": {
        "Mobile": {
          "value": 16,
          "type": "number"
        },
        "Tablet": {
          "value": 16,
          "type": "number"
        },
        "Desktop": {
          "value": 18,
          "type": "number"
        }
      }
    },
    "Badge": {
      "FontSize": {
        "Mobile": {
          "value": 10,
          "type": "number"
        },
        "Tablet": {
          "value": 11,
          "type": "number"
        },
        "Desktop": {
          "value": 11,
          "type": "number"
        }
      },
      "Weight": {
        "Mobile": {
          "value": 600,
          "type": "number"
        },
        "Tablet": {
          "value": 600,
          "type": "number"
        },
        "Desktop": {
          "value": 600,
          "type": "number"
        }
      },
      "LineHeight": {
        "Mobile": {
          "value": 12,
          "type": "number"
        },
        "Tablet": {
          "value": 14,
          "type": "number"
        },
        "Desktop": {
          "value": 14,
          "type": "number"
        }
      }
    },
    "Tag": {
      "FontSize": {
        "Mobile": {
          "value": 11,
          "type": "number"
        },
        "Tablet": {
          "value": 12,
          "type": "number"
        },
        "Desktop": {
          "value": 12,
          "type": "number"
        }
      },
      "LineHeight": {
        "Mobile": {
          "value": 14,
          "type": "number"
        },
        "Tablet": {
          "value": 16,
          "type": "number"
        },
        "Desktop": {
          "value": 0,
          "type": "number"
        }
      },
      "Weight": {
        "Mobile": {
          "value": 500,
          "type": "number"
        },
        "Tablet": {
          "value": 500,
          "type": "number"
        },
        "Desktop": {
          "value": 500,
          "type": "number"
        }
      }
    }
  },
  "Spacing/Mode 1": {
    "4 xxs": {
      "value": 4,
      "type": "number",
      "description": "فاصله آیکون و متن/فاصله بین چک باکس و لیبل/ فاصله بین برچسب در Badgeها"
    },
    "8 xs": {
      "value": 8,
      "type": "number",
      "description": "فاصله بین Label و Input\n\t•\tفاصله بین دو پاراگراف کوچک\n\t•\tفاصله داخلی (padding) المان‌های کوچک"
    },
    "12 s": {
      "value": 12,
      "type": "number",
      "description": "فاصله بین کارت‌ها در حالت موبایل\n\t•\tفاصله بین دو آیکون داخل Navigation\n\t•\tgap متوسط در Auto Layout"
    },
    "16 m": {
      "value": 16,
      "type": "number",
      "description": "•\tPadding دکمه‌ها\n\t•\tفاصله بین عنوان و متن\n\t•\tفاصله بین بخش‌های کوچک صفحه\n\t•\tفاصله داخلی کارت‌ها\n\t•\tفاصله بین ردیف فرم‌ها"
    },
    "20 l": {
      "value": 20,
      "type": "number",
      "description": "فاصله بین گروه کارت‌ها\n\t•\tفاصله بین ردیف‌های بزرگتر\n\t•\tفاصله بین تیتر H2 و سکشن‌ها"
    },
    "24 xl": {
      "value": 24,
      "type": "number",
      "description": "برای بلوک‌های بزرگ:\n\t•\tفاصله بالای بخش‌ها در موبایل\n\t•\tفاصله بین componentهای بزرگ\n\t•\tفاصله offset کارت‌ها"
    },
    "32 2xl": {
      "value": 32,
      "type": "number",
      "description": "در تبلت و دسکتاپ زیاد استفاده می‌شود:\n\t•\tفاصله بین سکشن‌های اصلی\n\t•\tفاصله زیر H1\n\t•\tفاصله بین containerهای اصلی"
    },
    "40 3xl": {
      "value": 40,
      "type": "number",
      "description": "برای:\n\t•\tفاصله بین Hero Section و بقیه صفحه\n\t•\tفاصله Padding در Desktop\n\t•\tفاصله بین major areas"
    },
    "48 4xl": {
      "value": 48,
      "type": "number",
      "description": "برای:\n\t•\tفاصله بین Hero Section و بقیه صفحه\n\t•\tفاصله Padding در Desktop\n\t•\tفاصله بین major areas"
    }
  },
  "Radius/Mode 1": {
    "2 xs": {
      "value": 2,
      "type": "number",
      "description": "برای عناصر بسیار ظریف و مینیمال. مناسب برای خطوط، باکس‌های خیلی کوچک و جزییات ظریف رابط کاربری."
    },
    "s 4": {
      "value": 4,
      "type": "number",
      "description": "برای دکمه‌های کوچک، فیلدهای فرم، تگ‌ها و عناصر ریز UI. گوشه استاندارد برای جزئیات کوچک."
    },
    "m 8": {
      "value": 8,
      "type": "number",
      "description": "رایج‌ترین گوشه در سیستم. مناسب کارت‌ها، باکس‌ها، فیلدهای ورودی، و کامپوننت‌های اصلی."
    },
    "l 12": {
      "value": 12,
      "type": "number",
      "description": "گوشه‌ی نرم‌تر برای سطوح بزرگ‌تر مثل کارت‌های برجسته، مودال‌ها، دیالوگ‌ها و پنل‌های مهم صفحه."
    },
    "xl 16": {
      "value": 16,
      "type": "number",
      "description": "برای کارت‌های بزرگ، سکشن‌ها، یا UIهای با هویت نرم‌تر. ایجاد حس صمیمیت و round بودن بیشتر."
    },
    "full 999": {
      "value": 999,
      "type": "number",
      "description": "برای ساخت شکل‌های قرصی (pill) مانند دکمه‌های گرد، تگ‌ها، نشان‌ها و هر عنصر با گوشه کاملاً گرد."
    }
  },
  "Border/Mode 1": {
    "1": {
      "value": 1,
      "type": "number",
      "description": "ضخامت پایه برای خطوط جداکننده، باکس‌های ساده و حالت معمولی فیلدهای فرم."
    },
    "2": {
      "value": 2,
      "type": "number",
      "description": "ضخامت برجسته‌تر برای حالت‌های Hover یا Focus روی دکمه‌ها و ورودی‌ها."
    },
    "3": {
      "value": 3,
      "type": "number",
      "description": "برای عناصر بسیار مهم یا نیازمند تأکید بصری بالا مانند کارت‌های برجسته یا هشدارها."
    }
  },
  "Opacity/Mode 1": {
    "Disabled": {
      "value": 40,
      "type": "number",
      "description": "همه‌جاهایی که یک المان دیگه قابل تعامل نیست:\n\t•\tدکمهٔ غیرفعال (Button Disabled)\n\t•\tلینک غیرفعال\n\t•\tInput / Select / Textarea غیرفعال\n\t•\tSwitch / Checkbox غیرفعال\n\t•\tآیکون‌های غیرفعال در Toolbar\n\t•\tکارت یا المانی که «قفل» شده\n\n✔ هدف:\n\nبلافاصله بفهمی این المان کار نمی‌کنه و کلیک‌پذیر نیست."
    },
    "Overlay": {
      "value": 60,
      "type": "number",
      "description": "همه‌جاهایی که چیزی «روی صفحه» ظاهر می‌شه:\n\t•\tپس‌زمینه پشت Modal\n\t•\tپس‌زمینه پشت Drawer یا Sidebar\n\t•\tپس‌زمینه پوستهٔ منوهای بازشونده (Menu Overlay)\n\t•\tزمانی که یک عکس یا گالری در حالت Lightbox باز می‌شه\n\t•\tوقتی اسکرین قفل موقت پیدا می‌کنه (Block UI)\n\n✔ هدف:\n\nتمرکز کاربر را از صفحه بگیره و روی عنصر اصلی ببرد.\nاما هنوز باید صفحه پشتش کمی دیده شود."
    },
    "Muted": {
      "value": 80,
      "type": "number",
      "description": "برای المان‌هایی که «اهمیت کم دارند» اما هنوز باید دیده شوند:\n\t•\tمتن های secondary\n(مثلاً توضیحات زیر عنوان، قیمت تخفیف‌خورده، دسته‌بندی)\n\t•\tآیکون‌های کم‌اهمیت\n(مثلاً آیکون info کوچک)\n\t•\tمتن Metadata\n(زمان انتشار، تعداد بازدید، موقعیت)\n\t•\tبرچسب‌های کم‌اهمیت (Tag Secondary)\n\t•\tدکمه‌های Ghost یا Secondary\n\n✔ هدف:\n\nاهمیت کمتر → ولی هنوز کاربر باید بتواند بخواند."
    },
    "Subtle": {
      "value": 90,
      "type": "number",
      "description": "برای «جزئیات خیلی ظریف» که باید دیده بشن ولی جلب توجه نکنن:\n\t•\tDivider / خط جداکننده‌ی ملایم\n\t•\tBorderهای خیلی لطیف\n(مثلاً دور کارت، دور input)\n\t•\tPlaceholder text داخل اینپوت‌ها\n\t•\tIcon های بسیار کم‌اهمیت\n(مثلاً آیکون Help کنار عنوان)\n\t•\tپس‌زمینه‌های خیلی کم‌رنگ (Subtle Background Tint)\n\t•\tسطرهای جدول که به‌صورت «زیگ‌زاگی» ملایم از هم جدا می‌شن\n\n✔ هدف:\n\nفقط کمی ساختار بده – نه بیشتر."
    }
  },
  "BreakPoint/Mode 1": {
    "Mobile": {
      "value": 480,
      "type": "number"
    },
    "Tablet": {
      "value": 768,
      "type": "number"
    },
    "Laptop": {
      "value": 1024,
      "type": "number"
    },
    "Desktop": {
      "value": 1440,
      "type": "number"
    }
  },
  "Layout/Mode 1": {
    "container": {
      "Mobile": {
        "value": 360,
        "type": "number"
      },
      "Tblet": {
        "value": 720,
        "type": "number"
      },
      "Laptop": {
        "value": 1200,
        "type": "number"
      },
      "Desktop": {
        "value": 1440,
        "type": "number"
      }
    }
  },
  "Grid/Mode 1": {
    "column": {
      "Mobile": {
        "value": 4,
        "type": "number"
      },
      "Tablet": {
        "value": 8,
        "type": "number"
      },
      "Desktop": {
        "value": 12,
        "type": "number"
      }
    }
  },
  "Shadow/Mode 1": {
    "none": {
      "value": 0,
      "type": "number"
    },
    "xs": {
      "value": 1,
      "type": "number"
    },
    "sm": {
      "value": 2,
      "type": "number"
    },
    "md": {
      "value": 3,
      "type": "number"
    },
    "lg": {
      "value": 4,
      "type": "number"
    },
    "xl": {
      "value": 5,
      "type": "number"
    }
  },
  "$themes": [],
  "$metadata": {
    "tokenSetOrder": [
      "global",
      "Color/Mode 1",
      "Boolean/Mode 1",
      "String/Mode 1",
      "Typography/Mode 1",
      "Spacing/Mode 1",
      "Radius/Mode 1",
      "Border/Mode 1",
      "Opacity/Mode 1",
      "BreakPoint/Mode 1",
      "Layout/Mode 1",
      "Grid/Mode 1",
      "Shadow/Mode 1"
    ]
  }
}